Workbook

Sheet README
A1: PLANTILLA MADRE DE COTIZACIÓN WEB — A&V Devs / Mr Monkey
A3: Objetivo | B3: Usar esta planilla como base estándar para cotizar proyectos web de cualquier cliente: landing, web corporativa, catálogo, ecommerce, reservas, integraciones, automatizaciones y mantenimiento.
A4: Flujo recomendado | B4: 1) Completar Datos_Cliente. 2) Ajustar Configuracion. 3) Seleccionar módulos en Calculadora. 4) Revisar Cronograma. 5) Definir Servicios_Mensuales. 6) Copiar Resumen_Cotizacion al documento/propuesta.
A5: Regla práctica | B5: La cotización base se calcula por horas estimadas x tarifa. Luego aplica complejidad, urgencia, contingencia, margen comercial e IVA opcional.
A6: Uso comercial | B6: La hoja permite mantener consistencia entre clientes, justificar valores profesionalmente y adaptar el alcance sin rehacer todo desde cero.
A7: Importante | B7: Los valores son editables. Debes calibrarlos con tu experiencia, mercado local chileno, tipo de cliente y dificultad real del proyecto.
A10: Hojas incluidas | B10: Datos_Cliente | C10: Configuracion | D10: Catalogo_Modulos | E10: Calculadora | F10: Cronograma | G10: Servicios_Mensuales | H10: Resumen_Cotizacion

Sheet Datos_Cliente
A1: DATOS DEL CLIENTE Y PROYECTO
A3: Fecha cotización | B3: 46153.551 | D3: Responsable | E3: Alfredo / Mr Monkey
A4: Cliente / Empresa | D4: RUT
A5: Contacto | D5: Email
A6: Teléfono | D6: Ciudad / País | E6: Chile
A7: Tipo de proyecto | B7: Web corporativa | D7: Estado actual | E7: Nuevo / Remodelación
A8: Dominio | D8: Hosting | E8: Cliente / Nuevo / No definido
A9: Sitio actual | D9: Referencia visual
A10: Objetivo principal | D10: Fecha deseada
A11: Público objetivo | D11: Prioridad | E11: Media
A12: Observaciones comerciales | D12: Notas internas

Sheet Configuracion
A1: CONFIGURACIÓN GENERAL DE CÁLCULO
A3: Parametro | B3: Valor | C3: Unidad | D3: Descripción | E3: Editable | F3: Notas
A4: Tarifa hora base | B4: 18000 | C4: CLP/h | D4: Tarifa interna mínima por hora de desarrollo/diseño/gestión. | E4: Sí | F4: Ajustar según seniority y mercado.
A5: Factor complejidad baja | B5: 1 | C5: factor | D5: Proyecto simple, pocas integraciones, contenido claro. | E5: Sí
A6: Factor complejidad media | B6: 1.2 | C6: factor | D6: Proyecto estándar con diseño personalizado y módulos comunes. | E6: Sí
A7: Factor complejidad alta | B7: 1.45 | C7: factor | D7: Proyecto con ecommerce, integraciones, automatizaciones o alta personalización. | E7: Sí
A8: Factor urgencia normal | B8: 1 | C8: factor | D8: Plazo cómodo. | E8: Sí
A9: Factor urgencia alta | B9: 1.25 | C9: factor | D9: Plazo ajustado o trabajo fuera de flujo normal. | E9: Sí
A10: Contingencia | B10: 0.12 | C10: % | D10: Riesgo técnico, cambios menores y colchón de implementación. | E10: Sí | F10: Recomendado 10% a 20%.
A11: Margen comercial | B11: 0.25 | C11: % | D11: Margen comercial/empresa sobre costo estimado. | E11: Sí
A12: IVA | B12: 0.19 | C12: % | D12: Impuesto si corresponde facturar afecto a IVA. | E12: Sí | F12: Chile: 19%.
A13: Aplicar IVA | B13: Sí | C13: Sí/No | D13: Controla si el resumen muestra total con IVA. | E13: Sí
A14: Descuento comercial | B14: 0 | C14: % | D14: Descuento opcional sobre subtotal antes de IVA. | E14: Sí
A15: Factor remodelación | B15: 0.85 | C15: factor | D15: Cuando ya existe página, dominio y hosting, pero requiere rediseño/remodelación. | E15: Sí | F15: Usar 0,75 a 0,95 según reutilización real.

Sheet Catalogo_Modulos
A1: CATÁLOGO ESTÁNDAR DE MÓDULOS WEB
A3: Categoria | B3: Modulo | C3: Descripción | D3: Horas baja | E3: Horas media | F3: Horas alta | G3: Entregable | H3: Aplica a | I3: Notas | J3: Fuente/Referencia
A4: Base | B4: Levantamiento de requerimientos | C4: Entrevista, alcance, objetivos, restricciones, propuesta base. | D4: 3 | E4: 5 | F4: 8 | G4: Documento de requerimientos | H4: Todos | I4: Siempre considerar.
A5: Base | B5: Arquitectura de información | C5: Mapa del sitio, estructura de navegación, jerarquía de contenidos. | D5: 3 | E5: 6 | F5: 10 | G5: Sitemap / estructura | H5: Todos | I5: Clave para evitar retrabajo.
A6: Diseño | B6: Dirección visual | C6: Paleta, tipografías, estilo de componentes, tono visual. | D6: 4 | E6: 8 | F6: 14 | G6: Mini design system | H6: Todos | I6: Puede crecer con branding.
A7: Diseño | B7: UI Home personalizada | C7: Diseño de portada principal responsive. | D7: 5 | E7: 10 | F7: 18 | G7: Home desktop/mobile | H7: Todos | I7: Se cotiza más si hay animaciones.
A8: Diseño | B8: Diseño de vistas internas | C8: Diseño de páginas internas, secciones y componentes reutilizables. | D8: 2 | E8: 4 | F8: 7 | G8: Vistas internas | H8: Todos | I8: Multiplicar por cantidad.
A9: Frontend | B9: Maquetación responsive | C9: Implementación mobile-first, tablet y desktop. | D9: 8 | E9: 16 | F9: 30 | G9: Sitio responsive | H9: Todos | I9: Base según número de vistas.
A10: Frontend | B10: Animaciones sutiles | C10: Microinteracciones, transiciones, efectos de scroll. | D10: 3 | E10: 7 | F10: 14 | G10: Animaciones | H10: Todos | I10: Evitar exceso si afecta performance.
A11: Contenido | B11: Carga de contenido | C11: Textos, imágenes, banners, secciones, enlaces. | D11: 2 | E11: 5 | F11: 10 | G11: Contenido cargado | H11: Todos | I11: Multiplicar por cantidad/lote.
A12: SEO | B12: SEO técnico básico | C12: Metatítulos, metadescripciones, headings, sitemap, robots. | D12: 4 | E12: 8 | F12: 14 | G12: SEO base | H12: Todos | I12: Complementa plan mensual SEO.
A13: Legal | B13: Páginas legales | C13: Políticas de privacidad, términos, cambios/devoluciones, cookies si aplica. | D13: 2 | E13: 4 | F13: 8 | G13: Páginas legales | H13: Corporativo/Ecommerce | I13: Cliente debe validar textos legales.
A14: Formulario | B14: Formulario de contacto | C14: Formulario con validaciones y envío por email. | D14: 3 | E14: 6 | F14: 10 | G14: Formulario funcional | H14: Todos | I14: Puede requerir SMTP/API.
A15: Formulario | B15: Formulario avanzado | C15: Cotización, reserva, filtros condicionales o adjuntos. | D15: 6 | E15: 12 | F15: 22 | G15: Formulario avanzado | H15: Servicios/Reservas | I15: Mayor QA.
... A18: Ecommerce | B18: Carrito y checkout | C18: Carrito, checkout, confirmación de compra. | D18: 10 | E18: 22 | F18: 45 | G18: Flujo de compra | H18: Ecommerce | I18: Depende de plataforma.
A19: Ecommerce | B19: Pasarela de pago | C19: Integración Webpay, MercadoPago u otra pasarela. | D19: 8 | E19: 16 | F19: 30 | G19: Pago integrado | H19: Ecommerce | I19: Puede requerir ambiente producción. | J19: https://www.transbankdevelopers.cl/
A20: Ecommerce | B20: Carga inicial de productos | C20: Carga de productos, variaciones, precios, fotos y atributos. | D20: 4 | E20: 10 | F20: 20 | G20: Productos cargados | H20: Ecommerce | I20: Multiplicar por lotes.
A21: Ecommerce | B21: Gestión de inventario | C21: Stock, SKU, variaciones, alertas básicas. | D21: 6 | E21: 14 | F21: 28 | G21: Inventario configurado | H21: Ecommerce | I21: Depende del CMS/plataforma.
A22: Reservas | B22: Agenda / reservas | C22: Sistema de reserva, disponibilidad, confirmaciones. | D22: 8 | E22: 18 | F22: 35 | G22: Agenda funcionando | H22: Servicios | I22: Puede requerir pagos/señales.
A23: Integración | B23: Analytics y tracking | C23: Google Analytics, Search Console, Pixel/Meta básico. | D23: 3 | E23: 6 | F23: 12 | G23: Tracking instalado | H23: Todos | I23: Solicitar accesos.
A24: QA | B24: Pruebas y correcciones | C24: QA responsive, formularios, navegación, performance básica. | D24: 5 | E24: 10 | F24: 20 | G24: Checklist QA | H24: Todos | I24: Siempre considerar.
A25: Deploy | B25: Publicación y traspaso | C25: Deploy, DNS, SSL, respaldos iniciales, capacitación breve. | D25: 4 | E25: 8 | F25: 16 | G25: Sitio publicado | H25: Todos | I25: Depende de hosting.

Sheet Calculadora
A1: CALCULADORA PRINCIPAL DE COTIZACIÓN
A3: Incluir | B3: Categoria | C3: Módulo | D3: Cantidad | E3: Complejidad | F3: Horas unitarias | G3: Horas base | H3: Factor proyecto | I3: Horas ajustadas | J3: Costo base | K3: Observación | L3: Entregable | M3: Prioridad
A4: Sí | B4: Base | C4: Levantamiento de requerimientos | D4: 1 | E4: Media | F4: =IFERROR(INDEX(Catalogo_Modulos!$D$4:$F$25,MATCH(C4,Catalogo_Modulos!$B$4:$B$25,0),MATCH(E4,{"Baja","Media","Alta"},0)),0) -> 5 | G4: =IF(A4="Sí",D4*F4,0) -> 5 | H4: =Configuracion!$B$15 -> 0.85 | I4: =G4*H4 -> 4.25 | J4: =I4*Configuracion!$B$4 -> 76500 | K4: Entrevista y definición de alcance | L4: Documento | M4: Alta
A5: Sí | B5: Base | C5: Arquitectura de información | D5: 1 | E5: Media | F5: =IFERROR(INDEX(Catalogo_Modulos!$D$4:$F$25,MATCH(C5,Catalogo_Modulos!$B$4:$B$25,0),MATCH(E5,{"Baja","Media","Alta"},0)),0) -> 6 | G5: =IF(A5="Sí",D5*F5,0) -> 6 | H5: =Configuracion!$B$15 -> 0.85 | I5: =G5*H5 -> 5.1 | J5: =I5*Configuracion!$B$4 -> 91800 | K5: Mapa del sitio y navegación | L5: Sitemap | M5: Alta
A6: Sí | B6: Diseño | C6: Dirección visual | D6: 1 | E6: Media | F6: =IFERROR(INDEX(Catalogo_Modulos!$D$4:$F$25,MATCH(C6,Catalogo_Modulos!$B$4:$B$25,0),MATCH(E6,{"Baja","Media","Alta"},0)),0) -> 8 | G6: =IF(A6="Sí",D6*F6,0) -> 8 | H6: =Configuracion!$B$15 -> 0.85 | I6: =G6*H6 -> 6.8 | J6: =I6*Configuracion!$B$4 -> 122400 | K6: Paleta, tipografías, componentes | L6: Mini design system | M6: Alta
A7: Sí | B7: Diseño | C7: UI Home personalizada | D7: 1 | E7: Media | F7: =IFERROR(INDEX(Catalogo_Modulos!$D$4:$F$25,MATCH(C7,Catalogo_Modulos!$B$4:$B$25,0),MATCH(E7,{"Baja","Media","Alta"},0)),0) -> 10 | G7: =IF(A7="Sí",D7*F7,0) -> 10 | H7: =Configuracion!$B$15 -> 0.85 | I7: =G7*H7 -> 8.5 | J7: =I7*Configuracion!$B$4 -> 153000 | K7: Home principal | L7: Diseño UI | M7: Alta
A8: Sí | B8: Diseño | C8: Diseño de vistas internas | D8: 5 | E8: Media | F8: =IFERROR(INDEX(Catalogo_Modulos!$D$4:$F$25,MATCH(C8,Catalogo_Modulos!$B$4:$B$25,0),MATCH(E8,{"Baja","Media","Alta"},0)),0) -> 4 | G8: =IF(A8="Sí",D8*F8,0) -> 20 | H8: =Configuracion!$B$15 -> 0.85 | I8: =G8*H8 -> 17 | J8: =I8*Configuracion!$B$4 -> 306000 | K8: Páginas internas | L8: Diseños | M8: Media
A9: Sí | B9: Frontend | C9: Maquetación responsive | D9: 1 | E9: Media | F9: =IFERROR(INDEX(Catalogo_Modulos!$D$4:$F$25,MATCH(C9,Catalogo_Modulos!$B$4:$B$25,0),MATCH(E9,{"Baja","Media","Alta"},0)),0) -> 16 | G9: =IF(A9="Sí",D9*F9,0) -> 16 | H9: =Configuracion!$B$15 -> 0.85 | I9: =G9*H9 -> 13.6 | J9: =I9*Configuracion!$B$4 -> 244800 | K9: Implementación responsive | L9: Frontend | M9: Alta
A10: Opcional | B10: Frontend | C10: Animaciones sutiles | D10: 1 | E10: Media | F10: =IFERROR(INDEX(Catalogo_Modulos!$D$4:$F$25,MATCH(C10,Catalogo_Modulos!$B$4:$B$25,0),MATCH(E10,{"Baja","Media","Alta"},0)),0) -> 7 | G10: =IF(A10="Sí",D10*F10,0) -> 0 | H10: =Configuracion!$B$15 -> 0.85 | I10: =G10*H10 -> 0 | J10: =I10*Configuracion!$B$4 -> 0 | K10: Microinteracciones | L10: Animaciones | M10: Media
A11: Sí | B11: Contenido | C11: Carga de contenido | D11: 1 | E11: Media | F11: =IFERROR(INDEX(Catalogo_Modulos!$D$4:$F$25,MATCH(C11,Catalogo_Modulos!$B$4:$B$25,0),MATCH(E11,{"Baja","Media","Alta"},0)),0) -> 5 | G11: =IF(A11="Sí",D11*F11,0) -> 5 | H11: =Configuracion!$B$15 -> 0.85 | I11: =G11*H11 -> 4.25 | J11: =I11*Configuracion!$B$4 -> 76500 | K11: Carga inicial de textos/imágenes | L11: Contenido | M11: Alta
A12: Sí | B12: SEO | C12: SEO técnico básico | D12: 1 | E12: Media | F12: =IFERROR(INDEX(Catalogo_Modulos!$D$4:$F$25,MATCH(C12,Catalogo_Modulos!$B$4:$B$25,0),MATCH(E12,{"Baja","Media","Alta"},0)),0) -> 8 | G12: =IF(A12="Sí",D12*F12,0) -> 8 | H12: =Configuracion!$B$15 -> 0.85 | I12: =G12*H12 -> 6.8 | J12: =I12*Configuracion!$B$4 -> 122400 | K12: SEO inicial | L12: SEO base | M12: Alta
A13: Sí | B13: Legal | C13: Páginas legales | D13: 1 | E13: Media | F13: =IFERROR(INDEX(Catalogo_Modulos!$D$4:$F$25,MATCH(C13,Catalogo_Modulos!$B$4:$B$25,0),MATCH(E13,{"Baja","Media","Alta"},0)),0) -> 4 | G13: =IF(A13="Sí",D13*F13,0) -> 4 | H13: =Configuracion!$B$15 -> 0.85 | I13: =G13*H13 -> 3.4 | J13: =I13*Configuracion!$B$4 -> 61200 | K13: Políticas y términos | L13: Páginas legales | M13: Alta
A14: Sí | B14: Formulario | C14: Formulario de contacto | D14: 1 | E14: Media | F14: =IFERROR(INDEX(Catalogo_Modulos!$D$4:$F$25,MATCH(C14,Catalogo_Modulos!$B$4:$B$25,0),MATCH(E14,{"Baja","Media","Alta"},0)),0) -> 6 | G14: =IF(A14="Sí",D14*F14,0) -> 6 | H14: =Configuracion!$B$15 -> 0.85 | I14: =G14*H14 -> 5.1 | J14: =I14*Configuracion!$B$4 -> 91800 | K14: Contacto funcional | L14: Formulario | M14: Alta
A15: Opcional | B15: Formulario | C15: Formulario avanzado | D15: 0 | E15: Media | F15: =IFERROR(INDEX(Catalogo_Modulos!$D$4:$F$25,MATCH(C15,Catalogo_Modulos!$B$4:$B$25,0),MATCH(E15,{"Baja","Media","Alta"},0)),0) -> 12 | G15: =IF(A15="Sí",D15*F15,0) -> 0 | H15: =Configuracion!$B$15 -> 0.85 | I15: =G15*H15 -> 0 | J15: =I15*Configuracion!$B$4 -> 0 | K15: Cotizador/reservas/adjuntos | L15: Formulario avanzado | M15: Media
... A25: Sí | B25: Deploy | C25: Publicación y traspaso | D25: 1 | E25: Media | F25: =IFERROR(INDEX(Catalogo_Modulos!$D$4:$F$25,MATCH(C25,Catalogo_Modulos!$B$4:$B$25,0),MATCH(E25,{"Baja","Media","Alta"},0)),0) -> 8 | G25: =IF(A25="Sí",D25*F25,0) -> 8 | H25: =Configuracion!$B$15 -> 0.85 | I25: =G25*H25 -> 6.8 | J25: =I25*Configuracion!$B$4 -> 122400 | K25: Deploy, SSL, capacitación | L25: Publicación | M25: Alta
A33: Resumen de cálculo | B33: Valor
A34: Horas base | B34: =SUM(G4:G25) -> 113
A35: Horas ajustadas | B35: =SUM(I4:I25) -> 96.05
A36: Costo directo | B36: =SUM(J4:J25) -> 1728900
A37: Contingencia | B37: =B36*Configuracion!$B$10 -> 207468
A38: Subtotal con contingencia | B38: =B36+B37 -> 1936368
A39: Margen comercial | B39: =B38*Configuracion!$B$11 -> 484092
A40: Subtotal neto | B40: =B38+B39 -> 2420460
A41: Descuento | B41: =B40*Configuracion!$B$14 -> 0
A42: Total neto | B42: =B40-B41 -> 2420460
A43: IVA | B43: =IF(Configuracion!$B$13="Sí",B42*Configuracion!$B$12,0) -> 459887.4
A44: Total con IVA | B44: =B42+B43 -> 2880347.4

Sheet Cronograma
A1: CRONOGRAMA ESTÁNDAR
A3: Fase | B3: Descripción | C3: Duración días | D3: Inicio estimado | E3: Fin estimado | F3: Responsable | G3: Entregable | H3: Estado
A4: 1. Levantamiento | B4: Reunión, objetivos, alcance y recopilación de material. | C4: 3 | D4: =TODAY()+3 -> 46156 | E4: =D4+C4 -> 46159 | F4: Cliente + Dev | G4: Requerimientos aprobados | H4: Pendiente
A5: 2. Diseño UX/UI | B5: Sitemap, dirección visual, vistas clave y validación. | C5: 7 | D5: =E4+1 -> 46160 | E5: =D5+C5 -> 46167 | F5: Dev/Diseño | G5: Diseño aprobado | H5: Pendiente
A6: 3. Desarrollo | B6: Construcción frontend/backend/CMS según alcance. | C6: 14 | D6: =E5+1 -> 46168 | E6: =D6+C6 -> 46182 | F6: Dev | G6: Versión funcional | H6: Pendiente
A7: 4. Contenido e integraciones | B7: Carga de contenido, SEO base, formularios, pagos o integraciones. | C7: 5 | D7: =E6+1 -> 46183 | E7: =D7+C7 -> 46188 | F7: Dev + Cliente | G7: Sitio prepublicado | H7: Pendiente
A8: 5. QA y ajustes | B8: Pruebas, correcciones, performance básica y revisión responsive. | C8: 5 | D8: =E7+1 -> 46189 | E8: =D8+C8 -> 46194 | F8: Dev | G8: Checklist QA | H8: Pendiente
A9: 6. Publicación y capacitación | B9: Deploy, DNS/SSL, entrega, capacitación y cierre. | C9: 2 | D9: =E8+1 -> 46195 | E9: =D9+C9 -> 46197 | F9: Dev + Cliente | G9: Sitio publicado | H9: Pendiente

Sheet Servicios_Mensuales
A1: SERVICIOS MENSUALES OPCIONALES
A3: Incluir | B3: Servicio | C3: Plan | D3: Valor mensual | E3: Horas incluidas | F3: SLA | G3: Entregables | H3: Observaciones | I3: Total mensual
A4: Sí | B4: Mantenimiento | C4: Esencial | D4: 85000 | E4: 2 | F4: Email 72h | G4: Actualizaciones mensuales, escaneo seguridad básico | H4: Tu precio publicado | I4: =IF(A4="Sí",D4,0) -> 85000
A5: Opcional | B5: SEO | C5: SEO Local | D5: 100000 | E5: 3 | F5: Mensual | G5: Google Business Profile, keywords locales, SEO on-page básico | H5: Tu precio publicado | I5: =IF(A5="Sí",D5,0) -> 0
A6: Opcional | B6: Redes sociales | C6: Plan Emprendedor | D6: 350000 | E6: 10 | F6: Mensual | G6: 1–2 redes, 8–10 publicaciones, copy y comunidad básica | H6: Tu precio publicado | I6: =IF(A6="Sí",D6,0) -> 0
A7: Opcional | B7: Bolsa de horas | C7: Soporte evolutivo | D7: 180000 | E7: 10 | F7: Según agenda | G7: Mejoras, ajustes, nuevas secciones pequeñas | H7: Editable | I7: =IF(A7="Sí",D7,0) -> 0
H10: Resumen mensual | I10: Valor
H11: Total mensual seleccionado | I11: =SUM(I4:I7) -> 85000
H12: Total anual estimado | I12: =I11*12 -> 1020000

Sheet Resumen_Cotizacion
A1: RESUMEN EJECUTIVO DE COTIZACIÓN
A3: Cliente | B3: =Datos_Cliente!B4 -> 0 | C3: Proyecto | D3: =Datos_Cliente!B7 -> Web corporativa | E3: Fecha | F3: =Datos_Cliente!B3 -> 46153.551
A4: Objetivo | B4: =Datos_Cliente!B10 -> 0 | C4: Referencia | D4: =Datos_Cliente!E9 -> 0 | E4: Prioridad | F4: =Datos_Cliente!E11 -> Media
A6: Concepto | B6: Valor | C6: Notas
A7: Horas base estimadas | B7: =Calculadora!B34 -> 113 | C7: Sin ajustes comerciales
A8: Horas ajustadas | B8: =Calculadora!B35 -> 96.05 | C8: Considera factor de remodelación/proyecto
A9: Subtotal neto | B9: =Calculadora!B42 -> 2420460 | C9: Antes de IVA
A10: IVA | B10: =Calculadora!B43 -> 459887.4 | C10: Según configuración
A11: TOTAL PROYECTO | B11: =Calculadora!B44 -> 2880347.4 | C11: Total estimado
A12: Mensualidad opcional | B12: =Servicios_Mensuales!I11 -> 85000 | C12: Servicios mensuales seleccionados
A15: Alcance recomendado para propuesta
A16: Esta cotización considera diseño/implementación web según módulos seleccionados, revisión responsive, SEO técnico base, QA funcional y publicación. Cambios mayores de alcance, integraciones no declaradas, licencias, fotografías profesionales, redacción legal especializada o costos de terceros se cotizan aparte.

Sheet Checklist_Requerimientos
A1: CHECKLIST DE TOMA DE REQUERIMIENTOS
A3: Área | B3: Pregunta | C3: Respuesta cliente | D3: Impacta costo | E3: Prioridad | F3: Estado | G3: Notas internas | H3: Responsable
A4: Negocio | B4: ¿Cuál es el objetivo principal del sitio? | D4: Sí | E4: Alta | F4: Pendiente | H4: Cliente
A5: Negocio | B5: ¿Quién es el público objetivo y ciudad/país principal? | D5: Sí | E5: Alta | F5: Pendiente | H5: Cliente
A6: Contenido | B6: ¿El cliente entregará textos, fotos, logo y branding? | D6: Sí | E6: Alta | F6: Pendiente | H6: Cliente
A7: Diseño | B7: ¿Existen referencias visuales aprobadas? | D7: Sí | E7: Alta | F7: Pendiente | H7: Cliente
A8: Estructura | B8: ¿Cuántas páginas/vistas necesita? | D8: Sí | E8: Alta | F8: Pendiente | H8: Dev
A9: Funcional | B9: ¿Requiere formularios, reservas, cotizador o subida de archivos? | D9: Sí | E9: Media | F9: Pendiente | H9: Dev
A10: Ecommerce | B10: ¿Venderá online? ¿Qué pasarela usará? | D10: Sí | E10: Alta | F10: Pendiente | H10: Cliente/Dev
A11: Ecommerce | B11: ¿Cuántos productos iniciales y variaciones tendrá? | D11: Sí | E11: Alta | F11: Pendiente | H11: Cliente
A12: Operación | B12: ¿Quién administrará productos/contenido después? | D12: Sí | E12: Media | F12: Pendiente | H12: Cliente
A13: SEO | B13: ¿Necesita SEO local, Google Business Profile o campañas? | D13: Sí | E13: Media | F13: Pendiente | H13: Dev
A14: Legal | B14: ¿Tiene políticas de privacidad, términos, cambios y devoluciones? | D14: Sí | E14: Alta | F14: Pendiente | H14: Cliente
A15: Infra | B15: ¿Ya tiene dominio, hosting, correos y accesos? | D15: Sí | E15: Alta | F15: Pendiente | H15: Cliente
... A17: Plazo | B17: ¿Hay fecha de lanzamiento o urgencia comercial? | D17: Sí | E17: Alta | F17: Pendiente | H17: Cliente
